{
  "id": 3,
  "name": "Big Billy",
  "price": 11.9,
  "rating": 4.2,
  "classification": 0,
  "description": "Corridas futuristas em pistas iluminadas por neon, com mecânicas de derrapagem e veículos customizáveis.",
  "tags": [
    { "name": "Corrida", "category": "gender" },
    { "name": "Futurista", "category": "gender" },
    { "name": "Arcade", "category": "gender" },
    { "name": "Multiplayer", "category": "resources" }
  ],
  "releaseDate": "2025-09-01T00:00:00.000Z",
  "publishingDate": "2024-03-20T00:00:00.000Z",
  "studio": { "name": "NeonWave Labs" },
  "publisher": { "name": "TurboPoint Studio" },
  "supportedLanguages": [
    { "name": "Português (Brasil)", "interface": true, "audio": true, "subtitles": true },
    { "name": "Inglês", "interface": true, "audio": true, "subtitles": true }
  ],
  "icon": "/images/games/big-billy-icon.png",
  "banner": "https://picsum.photos/seed/g3b/1200/500",
  "gallery": [
    { "type": "image", "src": "https://picsum.photos/400/200?5", "title": "Pista Neon" },
    { "type": "image", "src": "https://picsum.photos/400/200?6", "title": "Carro Customizado" }
  ],
  "additional": []
}
